stimulsoft_reports/__init__.py
stimulsoft_reports/base/StiCustomFont.py
stimulsoft_reports/base/StiFontCollection.py
stimulsoft_reports/base/StiLicense.py
stimulsoft_reports/base/StiLicenseStatic.py
stimulsoft_reports/base/__init__.py
stimulsoft_reports/classes/StiComponent.py
stimulsoft_reports/classes/StiComponentOptions.py
stimulsoft_reports/classes/StiElement.py
stimulsoft_reports/classes/StiEmailSettings.py
stimulsoft_reports/classes/StiFileResult.py
stimulsoft_reports/classes/StiHandler.py
stimulsoft_reports/classes/StiJavaScript.py
stimulsoft_reports/classes/StiJsElement.py
stimulsoft_reports/classes/StiNodeJs.py
stimulsoft_reports/classes/StiRequest.py
stimulsoft_reports/classes/StiResponse.py
stimulsoft_reports/classes/StiResult.py
stimulsoft_reports/classes/__init__.py
stimulsoft_reports/designer/StiDesigner.py
stimulsoft_reports/designer/__init__.py
stimulsoft_reports/designer/enums/StiDesignerPermissions.py
stimulsoft_reports/designer/enums/StiDesignerRibbonType.py
stimulsoft_reports/designer/enums/StiDesignerTheme.py
stimulsoft_reports/designer/enums/StiFirstDayOfWeek.py
stimulsoft_reports/designer/enums/StiInterfaceType.py
stimulsoft_reports/designer/enums/StiNewReportDictionary.py
stimulsoft_reports/designer/enums/StiPropertiesGridPosition.py
stimulsoft_reports/designer/enums/StiReportUnitType.py
stimulsoft_reports/designer/enums/StiUseAliases.py
stimulsoft_reports/designer/enums/StiWebUIIconSet.py
stimulsoft_reports/designer/enums/StiWizardType.py
stimulsoft_reports/designer/enums/__init__.py
stimulsoft_reports/designer/options/StiAppearanceOptions.py
stimulsoft_reports/designer/options/StiBandsOptions.py
stimulsoft_reports/designer/options/StiCrossBandsOptions.py
stimulsoft_reports/designer/options/StiDashboardElementsOptions.py
stimulsoft_reports/designer/options/StiDesignerOptions.py
stimulsoft_reports/designer/options/StiDictionaryOptions.py
stimulsoft_reports/designer/options/StiReportComponentsOptions.py
stimulsoft_reports-2026.1.2.dist-info/licenses/LICENSE.md
stimulsoft_reports-2026.1.2.dist-info/METADATA
stimulsoft_reports-2026.1.2.dist-info/WHEEL
stimulsoft_reports-2026.1.2.dist-info/top_level.txt
stimulsoft_reports-2026.1.2.dist-info/RECORD
