Metadata-Version: 2.4
Name: stimulsoft_reports
Version: 2026.1.2
Summary: A powerful and modern reporting tool for Python services.
Home-page: https://www.stimulsoft.com/en/products/reports-python
Author: Stimulsoft
Author-email: info@stimulsoft.com
License: https://www.stimulsoft.com/en/licensing/developers
Classifier: License :: Other/Proprietary License
Classifier: Framework :: Django
Classifier: Framework :: Flask
Classifier: Programming Language :: Python
Classifier: Programming Language :: Python :: 3.10
Classifier: Programming Language :: Python :: 3.11
Classifier: Programming Language :: Python :: 3.12
Classifier: Topic :: Office/Business
Classifier: Topic :: Software Development
Requires-Python: >=3.10
License-File: LICENSE.md
Requires-Dist: stimulsoft-data-adapters==2026.1.2
Provides-Extra: ext
Requires-Dist: stimulsoft-data-adapters[ext]==2026.1.2; extra == "ext"
Dynamic: author
Dynamic: author-email
Dynamic: classifier
Dynamic: description
Dynamic: description-content-type
Dynamic: home-page
Dynamic: license
Dynamic: license-file
Dynamic: provides-extra
Dynamic: requires-dist
Dynamic: requires-python
Dynamic: summary
